nora/__init__.py
nora/client.py
nora/utils.py
nora/anthropic/__init__.py
nora/anthropic/metadata_builder.py
nora/anthropic/streaming.py
nora/anthropic/types.py
nora/anthropic/utils.py
nora/gemini/__init__.py
nora/gemini/metadata_builder.py
nora/gemini/streaming.py
nora/gemini/types.py
nora/gemini/utils.py
nora/openai/__init__.py
nora/openai/metadata_builder.py
nora/openai/streaming.py
nora/openai/tool_tracer.py
nora/openai/types.py
nora/openai/utils.py
nora/patches/__init__.py
nora/patches/anthropic_patch.py
nora/patches/gemini_patch.py
nora/patches/openai_patch.py
nora_observability-1.0.20.dist-info/METADATA
nora_observability-1.0.20.dist-info/WHEEL
nora_observability-1.0.20.dist-info/top_level.txt
nora_observability-1.0.20.dist-info/RECORD
