Metadata-Version: 2.4
Name: nora-observability
Version: 1.0.20
Summary: AI Observability SDK - 자동으로 AI 라이브러리 호출을 trace합니다
Author: Nora Team
License: MIT
Project-URL: Homepage, https://github.com/nora-ai/observability-sdk
Project-URL: Documentation, https://docs.nora.ai
Project-URL: Repository, https://github.com/nora-ai/observability-sdk
Keywords: observability,ai,trace,monitoring,openai,anthropic
Classifier: Development Status :: 3 - Alpha
Classifier: Intended Audience :: Developers
Classifier: Programming Language :: Python :: 3
Classifier: Programming Language :: Python :: 3.8
Classifier: Programming Language :: Python :: 3.9
Classifier: Programming Language :: Python :: 3.10
Classifier: Programming Language :: Python :: 3.11
Classifier: Programming Language :: Python :: 3.12
Classifier: Programming Language :: Python :: 3.13
Requires-Python: >=3.8
Requires-Dist: requests>=2.28.0
Provides-Extra: dev
Requires-Dist: pytest>=7.0.0; extra == "dev"
Requires-Dist: pytest-asyncio>=0.21.0; extra == "dev"
Requires-Dist: black>=23.0.0; extra == "dev"
Requires-Dist: ruff>=0.1.0; extra == "dev"
Requires-Dist: google-genai>=1.47.0; extra == "dev"
Requires-Dist: anthropic>=0.40.0; extra == "dev"
Requires-Dist: openai>=1.0.0; extra == "dev"
